dosctl/__init__.py
dosctl/config.py
dosctl/main.py
dosctl/collections/__init__.py
dosctl/collections/archive_org.py
dosctl/collections/base.py
dosctl/collections/factory.py
dosctl/commands/delete.py
dosctl/commands/inspect.py
dosctl/commands/list.py
dosctl/commands/refresh.py
dosctl/commands/run.py
dosctl/commands/search.py
dosctl/commands/version.py
dosctl/lib/__init__.py
dosctl/lib/config_store.py
dosctl/lib/decorators.py
dosctl/lib/display.py
dosctl/lib/executables.py
dosctl/lib/game.py
dosctl/lib/system.py
dosctl/lib/ui.py
dosctl/lib/dosbox/__init__.py
dosctl/lib/dosbox/base.py
dosctl/lib/dosbox/launcher.py
dosctl/lib/dosbox/standard.py
dosctl/lib/platform/__init__.py
dosctl/lib/platform/base.py
dosctl/lib/platform/factory.py
dosctl/lib/platform/unix.py
dosctl/lib/platform/windows.py
dosctl-1.1.4.dist-info/licenses/LICENSE
dosctl-1.1.4.dist-info/METADATA
dosctl-1.1.4.dist-info/WHEEL
dosctl-1.1.4.dist-info/entry_points.txt
dosctl-1.1.4.dist-info/top_level.txt
dosctl-1.1.4.dist-info/RECORD
