Metadata-Version: 2.4
Name: dosctl
Version: 1.1.4
Summary: A command-line tool to manage and play DOS games via DOSBox.
Project-URL: Homepage, https://github.com/xesco/dosctl
Project-URL: Source, https://github.com/xesco/dosctl
Project-URL: Issues, https://github.com/xesco/dosctl/issues
Keywords: dos,games,retro,dosbox,cli
Classifier: Programming Language :: Python :: 3
Classifier: Programming Language :: Python :: 3.8
Classifier: Programming Language :: Python :: 3.9
Classifier: Programming Language :: Python :: 3.10
Classifier: Programming Language :: Python :: 3.11
Classifier: Programming Language :: Python :: 3.12
Classifier: License :: OSI Approved :: MIT License
Classifier: Operating System :: OS Independent
Classifier: Environment :: Console
Classifier: Topic :: Games/Entertainment
Classifier: Topic :: System :: Emulators
Requires-Python: >=3.8
License-File: LICENSE
Requires-Dist: click
Requires-Dist: requests
Requires-Dist: tqdm
Provides-Extra: dev
Requires-Dist: pytest; extra == "dev"
Dynamic: license-file
